main.py
setup.py
tarsire.egg-info/PKG-INFO
tarsire.egg-info/SOURCES.txt
tarsire.egg-info/dependency_links.txt
tarsire.egg-info/requires.txt
tarsire.egg-info/top_level.txt